tgraph/__init__.py
tgraph/join_feature_files.py
tgraph/nd_cloud.py
tgraph/nd_cloud_labeled.py
tgraph/static_graph.py
tgraph/static_graph_labeled.py
tgraph/temporal_graph.py
tgraph-1.0.1.dist-info/licenses/LICENSE
tgraph-1.0.1.dist-info/METADATA
tgraph-1.0.1.dist-info/WHEEL
tgraph-1.0.1.dist-info/entry_points.txt
tgraph-1.0.1.dist-info/top_level.txt
tgraph-1.0.1.dist-info/RECORD
