Metadata-Version: 2.4
Name: tgraph
Version: 1.0.1
Summary: Implementation of the t-graph package presented in the paper 'CallMine: Fraud Detection and Visualization of Million-Scale Call Graphs'.
Author-email: Mirela Cazzolato <mirelac@usp.br>
License-Expression: MIT
Project-URL: Homepage, https://github.com/joaovlpss/tgraph-fork
Keywords: tgraph,tgraph-spot,callmine,callmine-focus
Requires-Python: >=3.9
License-File: LICENSE
Requires-Dist: matplotlib
Requires-Dist: pandas
Requires-Dist: numpy
Requires-Dist: plotly
Requires-Dist: networkx
Requires-Dist: scipy
Dynamic: license-file
